advanced/RGBLight.v
module RGBLight(clk,light);
input clk;
output reg [2:0] light;
reg [1:0] state;
parameter RED = 3'b100, GREEN = 3'b010, BLUE = 3'b001;
parameter S0 = 0, S1 = 1, S2 = 2;
always @ (posedge clk)
case (state)
	S0: state <= S1;
	S1: state <= S2;
	S2: state <= S0;
	default: state <= S0;
endcase
always @ (state)
case (state)
	S0: light <= RED;
	S1: light <= GREEN;
	S2: light <= BLUE;
	default: light <= RED;
endcase
endmodule

advanced/testRGBLight.v
`timescale 1ms/100us
module testRGBLight;
reg clk;
wire [2:0] light;
RGBLight L (.clk(clk),.light(light));
always #5 clk = ~clk;
initial begin
$timeformat(-3,2,"ms",16);
clk = 1'b0;
#100 $stop;
end
initial begin
$dumpfile("lightz.vcd");
$dumpvars(0,testRGBLight);
$monitor("%t Light = %b",$time, light);
end
endmodule

advanced/lightz.vcd
$date
	Sun Nov 08 12:19:06 2020
$end
$version
	ModelSim Version 10.5b
$end
$timescale
	100us
$end

$scope module testRGBLight $end
$var reg 1 ! clk $end
$var wire 1 " light [2] $end
$var wire 1 # light [1] $end
$var wire 1 $ light [0] $end

$scope module L $end
$var parameter 3 % RED $end
$var parameter 3 & GREEN $end
$var parameter 3 ' BLUE $end
$var parameter 32 ( S0 $end
$var parameter 32 ) S1 $end
$var parameter 32 * S2 $end
$var wire 1 + clk $end
$var reg 3 , light [2:0] $end
$var reg 2 - state [1:0] $end
$upscope $end
$upscope $end
$enddefinitions $end
#0
$dumpvars
0!
bx ,
bx -
b100 %
b10 &
b1 '
b0 (
b1 )
b10 *
x$
x#
x"
0+
$end
#50
1!
1+
b0 -
b100 ,
0$
0#
1"
#100
0!
0+
#150
1!
1+
b1 -
b10 ,
1#
0"
#200
0!
0+
#250
1!
1+
b10 -
b1 ,
1$
0#
#300
0!
0+
#350
1!
1+
b0 -
b100 ,
0$
1"
#400
0!
0+
#450
1!
1+
b1 -
b10 ,
1#
0"
#500
0!
0+
#550
1!
1+
b10 -
b1 ,
1$
0#
#600
0!
0+
#650
1!
1+
b0 -
b100 ,
0$
1"
#700
0!
0+
#750
1!
1+
b1 -
b10 ,
1#
0"
#800
0!
0+
#850
1!
1+
b10 -
b1 ,
1$
0#
#900
0!
0+
#950
1!
1+
b0 -
b100 ,
0$
1"
